{"createdAt":1778169722,"version":1,"events":[{"state":"down","t":1.515208,"key":"O"},{"state":"down","t":1.517447,"key":"S"},{"state":"up","t":1.563956,"key":"S"},{"state":"up","t":1.606812,"key":"O"},{"state":"down","t":2.123314,"key":"Y"},{"state":"up","t":2.169576,"key":"Y"},{"state":"down","t":2.723285,"key":"T"},{"state":"up","t":2.769431,"key":"T"},{"state":"down","t":3.326985,"key":"O"},{"state":"down","t":3.336634,"key":"S"},{"state":"up","t":3.396953,"key":"S"},{"state":"up","t":3.419743,"key":"O"},{"state":"down","t":3.928603,"key":"Y"},{"state":"up","t":3.999861,"key":"Y"},{"state":"down","t":4.529746,"key":"T"},{"state":"up","t":4.576895,"key":"T"},{"state":"down","t":5.152561,"key":"P"},{"state":"up","t":5.183093,"key":"P"},{"state":"down","t":5.741853,"key":"O"},{"state":"down","t":5.744844,"key":"S"},{"state":"up","t":5.818942,"key":"S"},{"state":"up","t":5.820844,"key":"O"},{"state":"down","t":6.352704,"key":"Y"},{"state":"up","t":6.423782,"key":"Y"},{"state":"down","t":6.963768,"key":"T"},{"state":"up","t":7.031123,"key":"T"},{"state":"down","t":7.555147,"key":"O"},{"state":"down","t":7.56494,"key":"S"},{"state":"up","t":7.649234,"key":"O"},{"state":"up","t":7.651342,"key":"S"},{"state":"down","t":8.162136,"key":"Y"},{"state":"up","t":8.230305,"key":"Y"},{"state":"down","t":8.76611,"key":"T"},{"state":"up","t":8.860752,"key":"T"},{"state":"down","t":9.958355,"key":"O"},{"state":"down","t":9.962071,"key":"S"},{"state":"up","t":10.028294,"key":"S"},{"state":"up","t":10.051021,"key":"O"},{"state":"down","t":10.561023,"key":"Y"},{"state":"up","t":10.652705,"key":"Y"},{"state":"down","t":11.161923,"key":"T"},{"state":"up","t":11.232158,"key":"T"},{"state":"down","t":11.764945,"key":"O"},{"state":"down","t":11.767867,"key":"S"},{"state":"up","t":11.856711,"key":"O"},{"state":"up","t":11.85828,"key":"S"},{"state":"down","t":12.36751,"key":"Y"},{"state":"up","t":12.460487,"key":"Y"},{"state":"down","t":12.968474,"key":"T"},{"state":"up","t":13.014398,"key":"T"},{"state":"down","t":13.572923,"key":"P"},{"state":"up","t":13.619911,"key":"P"},{"state":"down","t":14.177026,"key":"O"},{"state":"down","t":14.179918,"key":"S"},{"state":"up","t":14.225193,"key":"S"},{"state":"up","t":14.269471,"key":"O"},{"state":"down","t":14.779895,"key":"Y"},{"state":"up","t":14.828652,"key":"Y"},{"state":"down","t":15.380339,"key":"T"},{"state":"up","t":15.473344,"key":"T"},{"state":"down","t":15.983722,"key":"O"},{"state":"down","t":15.987106,"key":"S"},{"state":"up","t":16.031646,"key":"O"},{"state":"up","t":16.033431,"key":"S"},{"state":"down","t":16.585284,"key":"Y"},{"state":"up","t":16.656852,"key":"Y"},{"state":"down","t":17.187653,"key":"T"},{"state":"up","t":17.258732,"key":"T"},{"state":"down","t":18.381553,"key":"O"},{"state":"down","t":18.385183,"key":"S"},{"state":"down","t":18.391144,"key":"Eight"},{"state":"down","t":18.397284,"key":"T"},{"state":"up","t":18.438129,"key":"S"},{"state":"up","t":18.453716,"key":"T"},{"state":"up","t":18.478476,"key":"O"},{"state":"up","t":18.480009,"key":"Eight"},{"state":"down","t":18.980656,"key":"A"},{"state":"down","t":18.98499,"key":"Y"},{"state":"up","t":19.035779,"key":"Y"},{"state":"up","t":19.082003,"key":"A"},{"state":"down","t":19.5926,"key":"O"},{"state":"down","t":19.597187,"key":"T"},{"state":"up","t":19.654265,"key":"T"},{"state":"up","t":19.667929,"key":"O"},{"state":"down","t":20.194893,"key":"O"},{"state":"down","t":20.199001,"key":"S"},{"state":"down","t":20.203234,"key":"Eight"},{"state":"down","t":20.207926,"key":"T"},{"state":"up","t":20.22536,"key":"O"},{"state":"up","t":20.246447,"key":"T"},{"state":"up","t":20.267375,"key":"S"},{"state":"up","t":20.290499,"key":"Eight"},{"state":"down","t":20.809138,"key":"O"},{"state":"down","t":20.822145,"key":"A"},{"state":"down","t":20.846747,"key":"Y"},{"state":"up","t":20.872555,"key":"A"},{"state":"up","t":20.890563,"key":"O"},{"state":"up","t":20.898507,"key":"Y"},{"state":"down","t":21.407497,"key":"U"},{"state":"down","t":21.417787,"key":"T"},{"state":"up","t":21.478776,"key":"U"},{"state":"up","t":21.501914,"key":"T"},{"state":"down","t":22.010028,"key":"P"},{"state":"up","t":22.058932,"key":"P"},{"state":"down","t":22.618975,"key":"O"},{"state":"down","t":22.622553,"key":"S"},{"state":"down","t":22.628666,"key":"Eight"},{"state":"down","t":22.638199,"key":"T"},{"state":"up","t":22.664247,"key":"T"},{"state":"up","t":22.674036,"key":"O"},{"state":"up","t":22.715023,"key":"S"},{"state":"up","t":22.716582,"key":"Eight"},{"state":"down","t":23.222567,"key":"A"},{"state":"down","t":23.231553,"key":"Y"},{"state":"up","t":23.291629,"key":"A"},{"state":"up","t":23.293708,"key":"Y"},{"state":"down","t":23.828342,"key":"O"},{"state":"down","t":23.834619,"key":"T"},{"state":"up","t":23.906676,"key":"T"},{"state":"up","t":23.921201,"key":"O"},{"state":"down","t":24.431508,"key":"O"},{"state":"down","t":24.434431,"key":"S"},{"state":"down","t":24.446999,"key":"Eight"},{"state":"down","t":24.450477,"key":"T"},{"state":"up","t":24.479604,"key":"O"},{"state":"up","t":24.500535,"key":"T"},{"state":"up","t":24.532546,"key":"S"},{"state":"up","t":24.534081,"key":"Eight"},{"state":"down","t":25.059916,"key":"A"},{"state":"down","t":25.064478,"key":"Y"},{"state":"up","t":25.114613,"key":"A"},{"state":"up","t":25.116877,"key":"Y"},{"state":"down","t":25.669505,"key":"T"},{"state":"up","t":25.765372,"key":"T"},{"state":"down","t":26.869915,"key":"U"},{"state":"down","t":26.872739,"key":"O"},{"state":"down","t":26.880579,"key":"S"},{"state":"down","t":26.884961,"key":"Eight"},{"state":"down","t":26.890356,"key":"T"},{"state":"up","t":26.91631,"key":"U"},{"state":"up","t":26.917733,"key":"Eight"},{"state":"up","t":26.939141,"key":"O"},{"state":"up","t":26.940714,"key":"S"},{"state":"up","t":26.945886,"key":"T"},{"state":"down","t":27.471991,"key":"O"},{"state":"down","t":27.474685,"key":"A"},{"state":"down","t":27.480368,"key":"Y"},{"state":"up","t":27.520304,"key":"A"},{"state":"up","t":27.521672,"key":"Y"},{"state":"up","t":27.545342,"key":"O"},{"state":"down","t":28.078181,"key":"O"},{"state":"down","t":28.081912,"key":"T"},{"state":"up","t":28.12932,"key":"T"},{"state":"up","t":28.130668,"key":"O"},{"state":"down","t":28.69228,"key":"U"},{"state":"down","t":28.69662,"key":"O"},{"state":"down","t":28.703531,"key":"S"},{"state":"down","t":28.707874,"key":"Eight"},{"state":"down","t":28.714255,"key":"T"},{"state":"up","t":28.739068,"key":"U"},{"state":"up","t":28.74124,"key":"O"},{"state":"up","t":28.7432,"key":"Eight"},{"state":"up","t":28.762146,"key":"T"},{"state":"up","t":28.787007,"key":"S"},{"state":"down","t":29.298063,"key":"O"},{"state":"down","t":29.306275,"key":"A"},{"state":"down","t":29.315153,"key":"Y"},{"state":"up","t":29.331322,"key":"O"},{"state":"up","t":29.343365,"key":"A"},{"state":"up","t":29.397134,"key":"Y"},{"state":"down","t":29.905505,"key":"U"},{"state":"down","t":29.911467,"key":"T"},{"state":"up","t":29.953703,"key":"T"},{"state":"up","t":29.982698,"key":"U"},{"state":"down","t":30.494797,"key":"P"},{"state":"down","t":30.49831,"key":"D"},{"state":"up","t":30.539177,"key":"D"},{"state":"up","t":30.586535,"key":"P"},{"state":"down","t":31.099636,"key":"O"},{"state":"down","t":31.102849,"key":"F"},{"state":"down","t":31.107991,"key":"Eight"},{"state":"down","t":31.115738,"key":"T"},{"state":"up","t":31.132637,"key":"T"},{"state":"up","t":31.150811,"key":"Eight"},{"state":"up","t":31.176088,"key":"O"},{"state":"up","t":31.17777,"key":"F"},{"state":"down","t":31.716287,"key":"H"},{"state":"down","t":31.723969,"key":"Y"},{"state":"up","t":31.764087,"key":"H"},{"state":"up","t":31.807106,"key":"Y"},{"state":"down","t":32.321441,"key":"S"},{"state":"down","t":32.324193,"key":"T"},{"state":"up","t":32.389368,"key":"T"},{"state":"up","t":32.391256,"key":"S"},{"state":"down","t":32.928323,"key":"O"},{"state":"down","t":32.936237,"key":"F"},{"state":"down","t":32.940693,"key":"Eight"},{"state":"down","t":32.946576,"key":"T"},{"state":"up","t":33.000883,"key":"Eight"},{"state":"up","t":33.004299,"key":"O"},{"state":"up","t":33.005952,"key":"F"},{"state":"up","t":33.007425,"key":"T"},{"state":"down","t":33.533584,"key":"H"},{"state":"down","t":33.536761,"key":"Y"},{"state":"up","t":33.60319,"key":"Y"},{"state":"up","t":33.604514,"key":"H"},{"state":"down","t":34.135617,"key":"S"},{"state":"down","t":34.145285,"key":"T"},{"state":"up","t":34.22895,"key":"S"},{"state":"up","t":34.230679,"key":"T"},{"state":"down","t":35.324285,"key":"U"},{"state":"down","t":35.328878,"key":"A"},{"state":"down","t":35.333268,"key":"Six"},{"state":"up","t":35.396526,"key":"A"},{"state":"up","t":35.397917,"key":"U"},{"state":"up","t":35.399463,"key":"Six"},{"state":"down","t":35.930449,"key":"P"},{"state":"down","t":35.934708,"key":"Y"},{"state":"up","t":35.979415,"key":"P"},{"state":"up","t":36.024652,"key":"Y"},{"state":"down","t":36.541638,"key":"U"},{"state":"down","t":36.545519,"key":"E"},{"state":"up","t":36.58863,"key":"U"},{"state":"up","t":36.590032,"key":"E"},{"state":"down","t":37.15139,"key":"U"},{"state":"down","t":37.161174,"key":"A"},{"state":"down","t":37.165826,"key":"Six"},{"state":"up","t":37.195857,"key":"U"},{"state":"up","t":37.197284,"key":"Six"},{"state":"up","t":37.216994,"key":"A"},{"state":"down","t":37.750228,"key":"P"},{"state":"down","t":37.754083,"key":"Y"},{"state":"up","t":37.798068,"key":"Y"},{"state":"up","t":37.821785,"key":"P"},{"state":"down","t":38.357347,"key":"LeftShift"},{"state":"down","t":38.35887,"key":"O"},{"state":"up","t":38.36346,"key":"LeftShift"},{"state":"down","t":38.365002,"key":"E"},{"state":"up","t":38.432241,"key":"O"},{"state":"up","t":38.451419,"key":"E"},{"state":"down","t":38.961194,"key":"LeftShift"},{"state":"down","t":38.962506,"key":"Q"},{"state":"up","t":38.966011,"key":"LeftShift"},{"state":"up","t":39.031836,"key":"Q"},{"state":"down","t":39.565674,"key":"U"},{"state":"down","t":39.568573,"key":"A"},{"state":"down","t":39.575175,"key":"Six"},{"state":"up","t":39.613122,"key":"U"},{"state":"up","t":39.639185,"key":"A"},{"state":"up","t":39.6593,"key":"Six"},{"state":"down","t":40.172258,"key":"P"},{"state":"down","t":40.175196,"key":"Y"},{"state":"up","t":40.248399,"key":"Y"},{"state":"up","t":40.272683,"key":"P"},{"state":"down","t":40.768199,"key":"U"},{"state":"down","t":40.771347,"key":"E"},{"state":"up","t":40.813662,"key":"E"},{"state":"up","t":40.858046,"key":"U"},{"state":"down","t":41.371271,"key":"Y"},{"state":"down","t":41.373967,"key":"Six"},{"state":"up","t":41.420677,"key":"Y"},{"state":"up","t":41.464954,"key":"Six"},{"state":"down","t":41.981199,"key":"LeftShift"},{"state":"down","t":41.982425,"key":"T"},{"state":"up","t":41.991761,"key":"LeftShift"},{"state":"up","t":42.068461,"key":"T"},{"state":"down","t":42.585783,"key":"E"},{"state":"up","t":42.680513,"key":"E"},{"state":"down","t":43.773016,"key":"U"},{"state":"down","t":43.777818,"key":"A"},{"state":"down","t":43.78173,"key":"Six"},{"state":"up","t":43.822778,"key":"A"},{"state":"up","t":43.846435,"key":"U"},{"state":"up","t":43.847796,"key":"Six"},{"state":"down","t":44.379325,"key":"P"},{"state":"down","t":44.390298,"key":"Y"},{"state":"up","t":44.430173,"key":"P"},{"state":"up","t":44.450262,"key":"Y"},{"state":"down","t":44.982268,"key":"U"},{"state":"down","t":44.985175,"key":"LeftShift"},{"state":"down","t":44.98649,"key":"S"},{"state":"up","t":44.99226,"key":"LeftShift"},{"state":"down","t":44.995976,"key":"E"},{"state":"up","t":45.030852,"key":"E"},{"state":"up","t":45.055425,"key":"S"},{"state":"up","t":45.076613,"key":"U"},{"state":"down","t":45.587241,"key":"U"},{"state":"down","t":45.590667,"key":"A"},{"state":"down","t":45.596602,"key":"Six"},{"state":"up","t":45.64032,"key":"A"},{"state":"up","t":45.667786,"key":"U"},{"state":"up","t":45.669359,"key":"Six"},{"state":"down","t":46.194891,"key":"P"},{"state":"down","t":46.197629,"key":"Y"},{"state":"up","t":46.240825,"key":"Y"},{"state":"up","t":46.266602,"key":"P"},{"state":"down","t":46.80131,"key":"LeftShift"},{"state":"down","t":46.803285,"key":"O"},{"state":"up","t":46.807022,"key":"LeftShift"},{"state":"down","t":46.81015,"key":"F"},{"state":"down","t":46.819456,"key":"E"},{"state":"up","t":46.88566,"key":"F"},{"state":"up","t":46.887176,"key":"E"},{"state":"up","t":46.929377,"key":"O"},{"state":"down","t":47.394833,"key":"LeftShift"},{"state":"down","t":47.396158,"key":"Q"},{"state":"up","t":47.405713,"key":"LeftShift"},{"state":"up","t":47.465793,"key":"Q"},{"state":"down","t":48.000025,"key":"LeftShift"},{"state":"down","t":48.001937,"key":"S"},{"state":"up","t":48.005353,"key":"LeftShift"},{"state":"down","t":48.007245,"key":"F"},{"state":"down","t":48.013238,"key":"LeftShift"},{"state":"down","t":48.015232,"key":"H"},{"state":"up","t":48.019836,"key":"LeftShift"},{"state":"down","t":48.022142,"key":"Six"},{"state":"up","t":48.072118,"key":"F"},{"state":"up","t":48.073477,"key":"Six"},{"state":"up","t":48.075749,"key":"H"},{"state":"up","t":48.092186,"key":"S"},{"state":"down","t":48.602545,"key":"F"},{"state":"down","t":48.605338,"key":"J"},{"state":"down","t":48.614422,"key":"Y"},{"state":"up","t":48.670974,"key":"J"},{"state":"up","t":48.672664,"key":"Y"},{"state":"up","t":48.694157,"key":"F"},{"state":"down","t":49.214224,"key":"P"},{"state":"down","t":49.217385,"key":"F"},{"state":"down","t":49.223202,"key":"E"},{"state":"up","t":49.262674,"key":"P"},{"state":"up","t":49.264188,"key":"F"},{"state":"up","t":49.285222,"key":"E"},{"state":"down","t":49.818484,"key":"LeftShift"},{"state":"down","t":49.820251,"key":"S"},{"state":"up","t":49.823265,"key":"LeftShift"},{"state":"down","t":49.824606,"key":"F"},{"state":"down","t":49.83061,"key":"LeftShift"},{"state":"down","t":49.833109,"key":"H"},{"state":"up","t":49.837592,"key":"LeftShift"},{"state":"down","t":49.838882,"key":"Six"},{"state":"up","t":49.867449,"key":"F"},{"state":"up","t":49.888652,"key":"S"},{"state":"up","t":49.89001,"key":"H"},{"state":"up","t":49.913207,"key":"Six"},{"state":"down","t":50.424435,"key":"F"},{"state":"down","t":50.42815,"key":"J"},{"state":"down","t":50.432076,"key":"Y"},{"state":"up","t":50.480239,"key":"F"},{"state":"up","t":50.486196,"key":"Y"},{"state":"up","t":50.496778,"key":"J"},{"state":"down","t":51.025944,"key":"P"},{"state":"down","t":51.02945,"key":"E"},{"state":"up","t":51.072838,"key":"E"},{"state":"up","t":51.097757,"key":"P"},{"state":"down","t":52.21889,"key":"U"},{"state":"down","t":52.230418,"key":"P"},{"state":"down","t":52.23615,"key":"LeftShift"},{"state":"down","t":52.237423,"key":"Four"},{"state":"up","t":52.240568,"key":"LeftShift"},{"state":"up","t":52.287925,"key":"P"},{"state":"up","t":52.289384,"key":"U"},{"state":"up","t":52.333512,"key":"Four"},{"state":"down","t":52.824479,"key":"LeftShift"},{"state":"down","t":52.826287,"key":"O"},{"state":"up","t":52.845316,"key":"LeftShift"},{"state":"down","t":52.846992,"key":"R"},{"state":"up","t":52.896452,"key":"R"},{"state":"up","t":52.947226,"key":"O"},{"state":"down","t":53.427355,"key":"U"},{"state":"down","t":53.430247,"key":"E"},{"state":"up","t":53.473061,"key":"U"},{"state":"up","t":53.474634,"key":"E"},{"state":"down","t":54.030648,"key":"U"},{"state":"down","t":54.034229,"key":"P"},{"state":"down","t":54.03995,"key":"LeftShift"},{"state":"down","t":54.041703,"key":"Four"},{"state":"up","t":54.047267,"key":"LeftShift"},{"state":"up","t":54.079999,"key":"U"},{"state":"up","t":54.081575,"key":"P"},{"state":"up","t":54.103796,"key":"Four"},{"state":"down","t":54.632572,"key":"LeftShift"},{"state":"down","t":54.63387,"key":"O"},{"state":"up","t":54.636771,"key":"LeftShift"},{"state":"down","t":54.638071,"key":"R"},{"state":"up","t":54.702185,"key":"R"},{"state":"up","t":54.724543,"key":"O"},{"state":"down","t":55.23417,"key":"LeftShift"},{"state":"down","t":55.235847,"key":"T"},{"state":"up","t":55.239208,"key":"LeftShift"},{"state":"down","t":55.240984,"key":"E"},{"state":"up","t":55.282581,"key":"E"},{"state":"up","t":55.304983,"key":"T"},{"state":"down","t":55.837958,"key":"LeftShift"},{"state":"down","t":55.83962,"key":"Q"},{"state":"up","t":55.84844,"key":"LeftShift"},{"state":"up","t":55.953041,"key":"Q"},{"state":"down","t":56.445548,"key":"LeftShift"},{"state":"down","t":56.446943,"key":"I"},{"state":"up","t":56.450017,"key":"LeftShift"},{"state":"down","t":56.451467,"key":"P"},{"state":"down","t":56.45618,"key":"LeftShift"},{"state":"down","t":56.458066,"key":"Four"},{"state":"up","t":56.462774,"key":"LeftShift"},{"state":"up","t":56.520665,"key":"P"},{"state":"up","t":56.543961,"key":"I"},{"state":"up","t":56.566472,"key":"Four"},{"state":"down","t":57.043571,"key":"LeftShift"},{"state":"down","t":57.045153,"key":"O"},{"state":"up","t":57.048236,"key":"LeftShift"},{"state":"down","t":57.049594,"key":"R"},{"state":"up","t":57.133896,"key":"R"},{"state":"up","t":57.145649,"key":"O"},{"state":"down","t":57.636737,"key":"U"},{"state":"down","t":57.640566,"key":"E"},{"state":"up","t":57.712736,"key":"U"},{"state":"up","t":57.714626,"key":"E"},{"state":"down","t":58.232686,"key":"U"},{"state":"down","t":58.236046,"key":"P"},{"state":"down","t":58.242651,"key":"LeftShift"},{"state":"down","t":58.246333,"key":"Four"},{"state":"up","t":58.251385,"key":"LeftShift"},{"state":"up","t":58.304735,"key":"P"},{"state":"up","t":58.306182,"key":"U"},{"state":"up","t":58.37124,"key":"Four"},{"state":"down","t":58.831843,"key":"LeftShift"},{"state":"down","t":58.833306,"key":"O"},{"state":"up","t":58.83648,"key":"LeftShift"},{"state":"down","t":58.838261,"key":"R"},{"state":"up","t":58.901168,"key":"O"},{"state":"up","t":58.924932,"key":"R"},{"state":"down","t":59.439842,"key":"E"},{"state":"up","t":59.509225,"key":"E"},{"state":"down","t":60.634786,"key":"U"},{"state":"down","t":60.639229,"key":"P"},{"state":"down","t":60.645729,"key":"LeftShift"},{"state":"down","t":60.647142,"key":"Four"},{"state":"up","t":60.652187,"key":"LeftShift"},{"state":"up","t":60.682247,"key":"P"},{"state":"up","t":60.707223,"key":"U"},{"state":"up","t":60.708862,"key":"Four"},{"state":"down","t":61.246852,"key":"LeftShift"},{"state":"down","t":61.248231,"key":"O"},{"state":"up","t":61.251634,"key":"LeftShift"},{"state":"down","t":61.253033,"key":"A"},{"state":"down","t":61.257374,"key":"R"},{"state":"up","t":61.301753,"key":"A"},{"state":"up","t":61.321667,"key":"O"},{"state":"up","t":61.323343,"key":"R"},{"state":"down","t":61.843153,"key":"U"},{"state":"down","t":61.855769,"key":"E"},{"state":"up","t":61.907548,"key":"U"},{"state":"up","t":61.912231,"key":"E"},{"state":"down","t":62.442746,"key":"U"},{"state":"down","t":62.446722,"key":"P"},{"state":"down","t":62.452379,"key":"LeftShift"},{"state":"down","t":62.454271,"key":"Four"},{"state":"up","t":62.458809,"key":"LeftShift"},{"state":"up","t":62.497059,"key":"P"},{"state":"up","t":62.518938,"key":"U"},{"state":"up","t":62.563492,"key":"Four"},{"state":"down","t":63.04949,"key":"LeftShift"},{"state":"down","t":63.051041,"key":"O"},{"state":"up","t":63.054253,"key":"LeftShift"},{"state":"down","t":63.055538,"key":"A"},{"state":"down","t":63.059625,"key":"R"},{"state":"up","t":63.122633,"key":"O"},{"state":"up","t":63.12438,"key":"R"},{"state":"up","t":63.126073,"key":"A"},{"state":"down","t":63.655285,"key":"U"},{"state":"down","t":63.658481,"key":"LeftShift"},{"state":"down","t":63.662359,"key":"S"},{"state":"up","t":63.666362,"key":"LeftShift"},{"state":"down","t":63.671158,"key":"E"},{"state":"up","t":63.724376,"key":"E"},{"state":"up","t":63.726126,"key":"S"},{"state":"up","t":63.752973,"key":"U"},{"state":"down","t":64.256995,"key":"LeftShift"},{"state":"down","t":64.258343,"key":"Q"},{"state":"up","t":64.262022,"key":"LeftShift"},{"state":"up","t":64.373796,"key":"Q"},{"state":"down","t":64.864425,"key":"LeftShift"},{"state":"down","t":64.865924,"key":"S"},{"state":"up","t":64.869306,"key":"LeftShift"},{"state":"down","t":64.872206,"key":"F"},{"state":"down","t":64.876188,"key":"LeftShift"},{"state":"down","t":64.878761,"key":"H"},{"state":"up","t":64.882332,"key":"LeftShift"},{"state":"down","t":64.887762,"key":"LeftShift"},{"state":"down","t":64.888953,"key":"Four"},{"state":"up","t":64.892898,"key":"LeftShift"},{"state":"up","t":64.909743,"key":"S"},{"state":"up","t":64.912571,"key":"F"},{"state":"up","t":64.962509,"key":"Four"},{"state":"up","t":65.004916,"key":"H"},{"state":"down","t":65.467996,"key":"F"},{"state":"down","t":65.470977,"key":"J"},{"state":"down","t":65.479603,"key":"R"},{"state":"up","t":65.515619,"key":"J"},{"state":"up","t":65.539504,"key":"F"},{"state":"up","t":65.540932,"key":"R"},{"state":"down","t":66.071586,"key":"P"},{"state":"down","t":66.075292,"key":"F"},{"state":"down","t":66.0822,"key":"E"},{"state":"up","t":66.122311,"key":"F"},{"state":"up","t":66.149081,"key":"P"},{"state":"up","t":66.172459,"key":"E"},{"state":"down","t":66.676415,"key":"LeftShift"},{"state":"down","t":66.678089,"key":"S"},{"state":"up","t":66.681494,"key":"LeftShift"},{"state":"down","t":66.683286,"key":"F"},{"state":"down","t":66.686498,"key":"LeftShift"},{"state":"down","t":66.687935,"key":"H"},{"state":"up","t":66.693175,"key":"LeftShift"},{"state":"down","t":66.696244,"key":"LeftShift"},{"state":"down","t":66.697761,"key":"Four"},{"state":"up","t":66.701155,"key":"LeftShift"},{"state":"up","t":66.728974,"key":"F"},{"state":"up","t":66.748788,"key":"H"},{"state":"up","t":66.79625,"key":"Four"},{"state":"up","t":66.798094,"key":"S"},{"state":"down","t":67.28373,"key":"F"},{"state":"down","t":67.286588,"key":"J"},{"state":"down","t":67.292326,"key":"R"},{"state":"up","t":67.332723,"key":"F"},{"state":"up","t":67.378549,"key":"J"},{"state":"up","t":67.3801,"key":"R"},{"state":"down","t":67.886287,"key":"P"},{"state":"down","t":67.889241,"key":"F"},{"state":"down","t":67.898368,"key":"E"},{"state":"up","t":67.932302,"key":"E"},{"state":"up","t":67.975663,"key":"P"},{"state":"up","t":67.977133,"key":"F"},{"state":"down","t":69.081251,"key":"O"},{"state":"down","t":69.08557,"key":"S"},{"state":"down","t":69.090152,"key":"Eight"},{"state":"up","t":69.117332,"key":"Eight"},{"state":"up","t":69.157923,"key":"O"},{"state":"up","t":69.181271,"key":"S"},{"state":"down","t":69.692333,"key":"A"},{"state":"down","t":69.697373,"key":"Y"},{"state":"up","t":69.762287,"key":"A"},{"state":"up","t":69.785593,"key":"Y"},{"state":"down","t":70.294957,"key":"O"},{"state":"down","t":70.29789,"key":"T"},{"state":"up","t":70.362881,"key":"T"},{"state":"up","t":70.385391,"key":"O"},{"state":"down","t":70.900616,"key":"O"},{"state":"down","t":70.90544,"key":"S"},{"state":"down","t":70.909353,"key":"Eight"},{"state":"up","t":70.95246,"key":"S"},{"state":"up","t":70.973431,"key":"O"},{"state":"up","t":70.975028,"key":"Eight"},{"state":"down","t":71.507421,"key":"A"},{"state":"down","t":71.525432,"key":"Y"},{"state":"up","t":71.549053,"key":"Y"},{"state":"up","t":71.550587,"key":"A"},{"state":"down","t":72.105879,"key":"U"},{"state":"down","t":72.108935,"key":"T"},{"state":"up","t":72.199164,"key":"T"},{"state":"up","t":72.203187,"key":"U"},{"state":"down","t":72.705947,"key":"P"},{"state":"up","t":72.776851,"key":"P"},{"state":"down","t":73.308458,"key":"O"},{"state":"down","t":73.315311,"key":"S"},{"state":"down","t":73.318932,"key":"Eight"},{"state":"up","t":73.385965,"key":"S"},{"state":"up","t":73.387368,"key":"Eight"},{"state":"up","t":73.426206,"key":"O"},{"state":"down","t":73.91431,"key":"A"},{"state":"down","t":73.917361,"key":"Y"},{"state":"up","t":73.961836,"key":"A"},{"state":"up","t":73.986129,"key":"Y"},{"state":"down","t":74.533499,"key":"O"},{"state":"down","t":74.538372,"key":"T"},{"state":"up","t":74.654904,"key":"T"},{"state":"up","t":74.656266,"key":"O"},{"state":"down","t":75.132781,"key":"I"},{"state":"down","t":75.135799,"key":"Eight"},{"state":"up","t":75.202791,"key":"I"},{"state":"up","t":75.244681,"key":"Eight"},{"state":"down","t":75.732759,"key":"U"},{"state":"up","t":75.780864,"key":"U"},{"state":"down","t":76.33676,"key":"T"},{"state":"up","t":76.432925,"key":"T"},{"state":"down","t":77.530793,"key":"O"},{"state":"down","t":77.535386,"key":"S"},{"state":"down","t":77.540618,"key":"F"},{"state":"down","t":77.54745,"key":"Eight"},{"state":"up","t":77.571029,"key":"S"},{"state":"up","t":77.634888,"key":"O"},{"state":"up","t":77.636856,"key":"F"},{"state":"up","t":77.63841,"key":"Eight"},{"state":"down","t":78.124492,"key":"A"},{"state":"down","t":78.130163,"key":"H"},{"state":"down","t":78.133674,"key":"Y"},{"state":"up","t":78.167093,"key":"Y"},{"state":"up","t":78.216601,"key":"A"},{"state":"up","t":78.218066,"key":"H"},{"state":"down","t":78.725589,"key":"O"},{"state":"down","t":78.730913,"key":"T"},{"state":"up","t":78.771928,"key":"O"},{"state":"up","t":78.811625,"key":"T"},{"state":"down","t":79.315679,"key":"O"},{"state":"down","t":79.318919,"key":"S"},{"state":"down","t":79.325508,"key":"F"},{"state":"down","t":79.331302,"key":"Eight"},{"state":"up","t":79.35791,"key":"S"},{"state":"up","t":79.359397,"key":"F"},{"state":"up","t":79.383124,"key":"Eight"},{"state":"up","t":79.384748,"key":"O"},{"state":"down","t":79.917167,"key":"A"},{"state":"down","t":79.919933,"key":"H"},{"state":"down","t":79.926496,"key":"Y"},{"state":"up","t":79.962244,"key":"A"},{"state":"up","t":79.963754,"key":"H"},{"state":"up","t":79.965452,"key":"Y"},{"state":"down","t":80.517038,"key":"O"},{"state":"down","t":80.519971,"key":"T"},{"state":"up","t":80.5646,"key":"O"},{"state":"up","t":80.5866,"key":"T"},{"state":"down","t":81.119424,"key":"P"},{"state":"down","t":81.123289,"key":"D"},{"state":"up","t":81.166426,"key":"P"},{"state":"up","t":81.213465,"key":"D"},{"state":"down","t":81.72297,"key":"O"},{"state":"down","t":81.725959,"key":"S"},{"state":"down","t":81.732067,"key":"J"},{"state":"down","t":81.739912,"key":"Eight"},{"state":"up","t":81.7682,"key":"Eight"},{"state":"up","t":81.79159,"key":"O"},{"state":"up","t":81.793273,"key":"J"},{"state":"up","t":81.795134,"key":"S"},{"state":"down","t":82.326101,"key":"A"},{"state":"down","t":82.330868,"key":"H"},{"state":"down","t":82.335765,"key":"Y"},{"state":"up","t":82.397765,"key":"A"},{"state":"up","t":82.399418,"key":"Y"},{"state":"up","t":82.418867,"key":"H"},{"state":"down","t":82.918654,"key":"O"},{"state":"down","t":82.922561,"key":"F"},{"state":"down","t":82.929284,"key":"T"},{"state":"up","t":82.9664,"key":"O"},{"state":"up","t":82.96781,"key":"T"},{"state":"up","t":83.014523,"key":"F"},{"state":"down","t":83.525484,"key":"O"},{"state":"down","t":83.530853,"key":"S"},{"state":"down","t":83.534859,"key":"H"},{"state":"down","t":83.54697,"key":"Eight"},{"state":"up","t":83.570924,"key":"H"},{"state":"up","t":83.58546,"key":"O"},{"state":"up","t":83.597289,"key":"Eight"},{"state":"up","t":83.620018,"key":"S"},{"state":"down","t":84.117865,"key":"A"},{"state":"down","t":84.124405,"key":"D"},{"state":"down","t":84.131937,"key":"Y"},{"state":"up","t":84.150533,"key":"Y"},{"state":"up","t":84.213721,"key":"A"},{"state":"up","t":84.215288,"key":"D"},{"state":"down","t":84.721613,"key":"O"},{"state":"down","t":84.725406,"key":"S"},{"state":"down","t":84.732513,"key":"T"},{"state":"up","t":84.771129,"key":"S"},{"state":"up","t":84.772817,"key":"T"},{"state":"up","t":84.814806,"key":"O"},{"state":"down","t":85.918084,"key":"O"},{"state":"down","t":85.921532,"key":"S"},{"state":"down","t":85.927231,"key":"F"},{"state":"down","t":85.933791,"key":"Eight"},{"state":"up","t":85.963521,"key":"F"},{"state":"up","t":85.965394,"key":"O"},{"state":"up","t":86.00799,"key":"S"},{"state":"up","t":86.009527,"key":"Eight"},{"state":"down","t":86.52637,"key":"A"},{"state":"down","t":86.54528,"key":"H"},{"state":"down","t":86.553852,"key":"Y"},{"state":"up","t":86.571813,"key":"H"},{"state":"up","t":86.604688,"key":"A"},{"state":"up","t":86.606163,"key":"Y"},{"state":"down","t":87.160776,"key":"O"},{"state":"down","t":87.165697,"key":"T"},{"state":"up","t":87.185924,"key":"O"},{"state":"up","t":87.208259,"key":"T"},{"state":"down","t":87.744742,"key":"O"},{"state":"down","t":87.747877,"key":"S"},{"state":"down","t":87.75352,"key":"F"},{"state":"down","t":87.764689,"key":"Eight"},{"state":"up","t":87.817317,"key":"O"},{"state":"up","t":87.818653,"key":"S"},{"state":"up","t":87.819885,"key":"F"},{"state":"up","t":87.824229,"key":"Eight"},{"state":"down","t":88.348599,"key":"A"},{"state":"down","t":88.351662,"key":"H"},{"state":"down","t":88.358499,"key":"Y"},{"state":"up","t":88.420574,"key":"A"},{"state":"up","t":88.422527,"key":"Y"},{"state":"up","t":88.443563,"key":"H"},{"state":"down","t":88.951093,"key":"O"},{"state":"down","t":88.953953,"key":"T"},{"state":"up","t":88.998079,"key":"O"},{"state":"up","t":89.042923,"key":"T"},{"state":"down","t":89.578525,"key":"P"},{"state":"down","t":89.581769,"key":"D"},{"state":"up","t":89.608619,"key":"P"},{"state":"up","t":89.656266,"key":"D"},{"state":"down","t":90.170164,"key":"O"},{"state":"down","t":90.186263,"key":"S"},{"state":"down","t":90.189835,"key":"J"},{"state":"down","t":90.198135,"key":"Eight"},{"state":"up","t":90.215386,"key":"J"},{"state":"up","t":90.233627,"key":"O"},{"state":"up","t":90.235826,"key":"Eight"},{"state":"up","t":90.267352,"key":"S"},{"state":"down","t":90.781339,"key":"A"},{"state":"down","t":90.785972,"key":"H"},{"state":"down","t":90.790164,"key":"Y"},{"state":"up","t":90.833518,"key":"A"},{"state":"up","t":90.835137,"key":"H"},{"state":"up","t":90.836872,"key":"Y"},{"state":"down","t":91.392352,"key":"O"},{"state":"down","t":91.397019,"key":"F"},{"state":"down","t":91.408323,"key":"T"},{"state":"up","t":91.428689,"key":"O"},{"state":"up","t":91.484551,"key":"F"},{"state":"up","t":91.486201,"key":"T"},{"state":"down","t":92.009806,"key":"O"},{"state":"down","t":92.02372,"key":"S"},{"state":"down","t":92.026714,"key":"H"},{"state":"down","t":92.035105,"key":"Eight"},{"state":"up","t":92.053966,"key":"S"},{"state":"up","t":92.05741,"key":"O"},{"state":"up","t":92.083195,"key":"H"},{"state":"up","t":92.084941,"key":"Eight"},{"state":"down","t":92.608527,"key":"A"},{"state":"down","t":92.613601,"key":"D"},{"state":"down","t":92.636723,"key":"Y"},{"state":"up","t":92.675034,"key":"D"},{"state":"up","t":92.68654,"key":"A"},{"state":"up","t":92.687998,"key":"Y"},{"state":"down","t":93.2208,"key":"O"},{"state":"down","t":93.22382,"key":"S"},{"state":"down","t":93.230206,"key":"T"},{"state":"up","t":93.290608,"key":"S"},{"state":"up","t":93.292455,"key":"T"},{"state":"up","t":93.293967,"key":"O"},{"state":"down","t":94.414824,"key":"S"},{"state":"down","t":94.41864,"key":"F"},{"state":"down","t":94.42467,"key":"J"},{"state":"down","t":94.429715,"key":"L"},{"state":"down","t":94.434433,"key":"Eight"},{"state":"up","t":94.451514,"key":"L"},{"state":"up","t":94.453175,"key":"Eight"},{"state":"up","t":94.470667,"key":"F"},{"state":"up","t":94.472407,"key":"J"},{"state":"up","t":94.493234,"key":"S"},{"state":"down","t":95.004225,"key":"A"},{"state":"down","t":95.007028,"key":"D"},{"state":"down","t":95.015715,"key":"K"},{"state":"down","t":95.018862,"key":"Y"},{"state":"up","t":95.035749,"key":"D"},{"state":"up","t":95.071184,"key":"A"},{"state":"up","t":95.099663,"key":"K"},{"state":"up","t":95.101049,"key":"Y"},{"state":"down","t":95.608269,"key":"O"},{"state":"down","t":95.617266,"key":"F"},{"state":"down","t":95.626689,"key":"H"},{"state":"down","t":95.632427,"key":"T"},{"state":"up","t":95.657311,"key":"F"},{"state":"up","t":95.658695,"key":"H"},{"state":"up","t":95.678804,"key":"O"},{"state":"up","t":95.703632,"key":"T"},{"state":"down","t":96.210927,"key":"O"},{"state":"down","t":96.215083,"key":"S"},{"state":"down","t":96.220972,"key":"F"},{"state":"down","t":96.224708,"key":"Eight"},{"state":"up","t":96.285256,"key":"O"},{"state":"up","t":96.286822,"key":"S"},{"state":"up","t":96.288273,"key":"Eight"},{"state":"up","t":96.307595,"key":"F"},{"state":"down","t":96.817084,"key":"A"},{"state":"down","t":96.820129,"key":"H"},{"state":"down","t":96.826637,"key":"Y"},{"state":"up","t":96.864214,"key":"H"},{"state":"up","t":96.910809,"key":"Y"},{"state":"up","t":96.9137,"key":"A"},{"state":"down","t":97.422543,"key":"S"},{"state":"down","t":97.425666,"key":"F"},{"state":"down","t":97.434783,"key":"J"},{"state":"down","t":97.439317,"key":"T"},{"state":"up","t":97.468283,"key":"F"},{"state":"up","t":97.515009,"key":"S"},{"state":"up","t":97.516825,"key":"J"},{"state":"up","t":97.518251,"key":"T"},{"state":"down","t":98.022585,"key":"D"},{"state":"down","t":98.031512,"key":"H"},{"state":"down","t":98.03531,"key":"U"},{"state":"up","t":98.088506,"key":"D"},{"state":"up","t":98.089885,"key":"H"},{"state":"up","t":98.092199,"key":"U"},{"state":"down","t":98.626816,"key":"O"},{"state":"down","t":98.631744,"key":"S"},{"state":"down","t":98.636816,"key":"J"},{"state":"down","t":98.641536,"key":"Eight"},{"state":"up","t":98.658756,"key":"J"},{"state":"up","t":98.675891,"key":"O"},{"state":"up","t":98.677511,"key":"S"},{"state":"up","t":98.722637,"key":"Eight"},{"state":"down","t":99.2359,"key":"A"},{"state":"down","t":99.246437,"key":"H"},{"state":"down","t":99.250845,"key":"Y"},{"state":"up","t":99.274119,"key":"H"},{"state":"up","t":99.275668,"key":"Y"},{"state":"up","t":99.327782,"key":"A"},{"state":"down","t":99.840964,"key":"O"},{"state":"down","t":99.844065,"key":"F"},{"state":"down","t":99.850268,"key":"T"},{"state":"up","t":99.879244,"key":"F"},{"state":"up","t":99.881361,"key":"T"},{"state":"up","t":99.898508,"key":"O"},{"state":"down","t":100.452553,"key":"O"},{"state":"down","t":100.455691,"key":"S"},{"state":"down","t":100.460817,"key":"H"},{"state":"down","t":100.46793,"key":"Eight"},{"state":"up","t":100.484624,"key":"H"},{"state":"up","t":100.545675,"key":"O"},{"state":"up","t":100.547283,"key":"Eight"},{"state":"up","t":100.54886,"key":"S"},{"state":"down","t":101.054194,"key":"A"},{"state":"down","t":101.057265,"key":"D"},{"state":"down","t":101.06578,"key":"Y"},{"state":"up","t":101.097136,"key":"Y"},{"state":"up","t":101.118474,"key":"A"},{"state":"up","t":101.136925,"key":"D"},{"state":"down","t":101.647324,"key":"O"},{"state":"down","t":101.650639,"key":"S"},{"state":"down","t":101.655436,"key":"T"},{"state":"up","t":101.695296,"key":"O"},{"state":"up","t":101.697295,"key":"S"},{"state":"up","t":101.699045,"key":"T"},{"state":"down","t":102.828236,"key":"L"},{"state":"down","t":102.831902,"key":"O"},{"state":"up","t":102.871607,"key":"L"},{"state":"up","t":102.919575,"key":"O"},{"state":"down","t":103.436983,"key":"K"},{"state":"down","t":103.440245,"key":"Y"},{"state":"up","t":103.484369,"key":"K"},{"state":"up","t":103.528369,"key":"Y"},{"state":"down","t":104.042012,"key":"H"},{"state":"down","t":104.046874,"key":"T"},{"state":"up","t":104.086947,"key":"T"},{"state":"up","t":104.132311,"key":"H"},{"state":"down","t":104.641152,"key":"L"},{"state":"down","t":104.644173,"key":"O"},{"state":"up","t":104.73444,"key":"O"},{"state":"up","t":104.736417,"key":"L"},{"state":"down","t":105.246613,"key":"K"},{"state":"down","t":105.251127,"key":"Y"},{"state":"up","t":105.29831,"key":"Y"},{"state":"up","t":105.317466,"key":"K"},{"state":"down","t":105.849235,"key":"F"},{"state":"down","t":105.852937,"key":"T"},{"state":"up","t":105.894721,"key":"F"},{"state":"up","t":105.917972,"key":"T"},{"state":"down","t":106.450714,"key":"P"},{"state":"up","t":106.500683,"key":"P"},{"state":"down","t":107.065452,"key":"L"},{"state":"down","t":107.078419,"key":"O"},{"state":"up","t":107.10846,"key":"O"},{"state":"up","t":107.138638,"key":"L"},{"state":"down","t":107.666858,"key":"K"},{"state":"down","t":107.670056,"key":"Y"},{"state":"up","t":107.736395,"key":"Y"},{"state":"up","t":107.737905,"key":"K"},{"state":"down","t":108.26856,"key":"H"},{"state":"down","t":108.2716,"key":"T"},{"state":"up","t":108.361023,"key":"H"},{"state":"up","t":108.362692,"key":"T"},{"state":"down","t":108.870909,"key":"L"},{"state":"down","t":108.873817,"key":"O"},{"state":"up","t":108.921153,"key":"O"},{"state":"up","t":108.942035,"key":"L"},{"state":"down","t":109.472681,"key":"K"},{"state":"down","t":109.476881,"key":"Y"},{"state":"up","t":109.548666,"key":"Y"},{"state":"up","t":109.550441,"key":"K"},{"state":"down","t":110.073804,"key":"S"},{"state":"down","t":110.082616,"key":"L"},{"state":"down","t":110.091228,"key":"T"},{"state":"up","t":110.142682,"key":"S"},{"state":"up","t":110.167091,"key":"T"},{"state":"up","t":110.168516,"key":"L"},{"state":"down","t":111.25662,"key":"L"},{"state":"down","t":111.265511,"key":"O"},{"state":"up","t":111.347937,"key":"L"},{"state":"up","t":111.349466,"key":"O"},{"state":"down","t":111.862414,"key":"K"},{"state":"down","t":111.865446,"key":"V"},{"state":"down","t":111.871078,"key":"Y"},{"state":"up","t":111.908084,"key":"K"},{"state":"up","t":111.954803,"key":"V"},{"state":"up","t":111.95635,"key":"Y"},{"state":"down","t":112.468115,"key":"H"},{"state":"down","t":112.476263,"key":"L"},{"state":"down","t":112.485193,"key":"T"},{"state":"up","t":112.535069,"key":"H"},{"state":"up","t":112.536677,"key":"L"},{"state":"up","t":112.538238,"key":"T"},{"state":"down","t":113.066405,"key":"L"},{"state":"down","t":113.069321,"key":"O"},{"state":"up","t":113.158247,"key":"O"},{"state":"up","t":113.160091,"key":"L"},{"state":"down","t":113.669797,"key":"K"},{"state":"down","t":113.672619,"key":"V"},{"state":"down","t":113.68173,"key":"Y"},{"state":"up","t":113.720345,"key":"Y"},{"state":"up","t":113.739735,"key":"V"},{"state":"up","t":113.742009,"key":"K"},{"state":"down","t":114.270319,"key":"L"},{"state":"down","t":114.27312,"key":"T"},{"state":"up","t":114.34012,"key":"L"},{"state":"up","t":114.363362,"key":"T"},{"state":"down","t":114.875339,"key":"B"},{"state":"down","t":114.901339,"key":"P"},{"state":"up","t":114.921256,"key":"P"},{"state":"up","t":114.922634,"key":"B"},{"state":"down","t":115.469,"key":"L"},{"state":"down","t":115.473505,"key":"O"},{"state":"up","t":115.509645,"key":"O"},{"state":"up","t":115.557542,"key":"L"},{"state":"down","t":116.064868,"key":"K"},{"state":"down","t":116.068432,"key":"V"},{"state":"down","t":116.074181,"key":"Y"},{"state":"up","t":116.135396,"key":"K"},{"state":"up","t":116.15896,"key":"V"},{"state":"up","t":116.160863,"key":"Y"},{"state":"down","t":116.66654,"key":"H"},{"state":"down","t":116.669299,"key":"L"},{"state":"down","t":116.674744,"key":"T"},{"state":"up","t":116.712085,"key":"H"},{"state":"up","t":116.736894,"key":"L"},{"state":"up","t":116.738505,"key":"T"},{"state":"down","t":117.27498,"key":"L"},{"state":"down","t":117.278264,"key":"O"},{"state":"up","t":117.323234,"key":"L"},{"state":"up","t":117.36848,"key":"O"},{"state":"down","t":117.874361,"key":"K"},{"state":"down","t":117.877438,"key":"V"},{"state":"down","t":117.883956,"key":"Y"},{"state":"up","t":117.924707,"key":"V"},{"state":"up","t":117.926496,"key":"K"},{"state":"up","t":117.959401,"key":"Y"},{"state":"down","t":118.541213,"key":"L"},{"state":"down","t":118.544176,"key":"T"},{"state":"up","t":118.585747,"key":"L"},{"state":"up","t":118.587557,"key":"T"}],"author":"C418","type":"keyboard_macro","name":"Haggstorm"}